{"data":[{"id":"1","deviceId":"1","name":"Zone A Primary","model":"Lumatek Zeus 600W","address":"zone-a-primary","status":"off","value":null,"online":true,"updatedAt":"2025-10-18T19:47:19Z","controlInterface":"dali","lastKnown":{"brightness":10,"spectrum":3000,"updated_at":1760831239}},{"id":"2","deviceId":"2","name":"Zone B Supplemental","model":"Philips GreenPower LED Toplighting","address":"zone-b-supplemental","status":"off","value":null,"online":true,"updatedAt":"2025-10-18T19:47:19Z","controlInterface":"pwm","lastKnown":{"brightness":5,"spectrum":2700,"updated_at":1760831239}},{"id":"3","deviceId":"3","name":"Propagation Rack","model":"Fluence SPYDR 2i","address":"propagation-rack","status":"off","value":null,"online":true,"updatedAt":"2025-10-18T19:47:19Z","controlInterface":"kasa","lastKnown":{"brightness":15,"spectrum":3200,"updated_at":1760831239}}],"count":3,"updatedAt":"2025-10-18T21:07:52Z"}