{
  "rooms": [
    {
      "id": "room-prop",
      "name": "Propagation Bay",
      "location": "Main Campus",
      "hardwareCats": ["light", "dehumidifier"],
      "hardwareOrder": ["light", "dehumidifier"],
      "layout": {
        "type": "benches",
        "rows": 2,
        "racks": 1,
        "levels": 1
      },
      "zones": ["Propagation North"],
      "fixtures": [
        {
          "id": "fixture-prop-toplight",
          "vendor": "GROW3",
          "model": "TopLight MH Model-300W-22G12",
          "count": 2,
          "zone": "Propagation North"
        }
      ],
      "controlMethod": "local",
      "devices": [
        { "id": "light-001", "type": "light" },
        { "id": "light-002", "type": "light" }
      ],
      "sensors": {
        "categories": ["environment"],
        "placements": {
          "environment": [
            { "type": "Temp/Humidity", "location": "center canopy" },
            { "type": "CO2", "location": "north aisle" }
          ]
        }
      },
      "energy": "120V dedicated",
      "energyHours": 18,
      "targetPpfd": 320,
      "photoperiod": 18,
      "connectivity": {
        "hasHub": true,
        "hubType": "SwitchBot Hub 2",
        "hubIp": "192.168.1.52",
        "cloudTenant": "SwitchBot"
      },
      "roles": {
        "admin": ["alex.nguyen"],
        "operator": ["samantha.hughes"],
        "viewer": []
      },
      "grouping": {
        "groups": ["propagation-north"],
        "planId": "propagation-daylight",
        "scheduleId": "schedule-prop-18h"
      },
      "seriesCount": 1,
      "category": {
        "light": {
          "selectedEquipment": [
            {
              "category": "light",
              "vendor": "GROW3",
              "model": "TopLight MH Model-300W-22G12",
              "count": 2,
              "zone": "Propagation North"
            }
          ],
          "wifi": true,
          "wired": false,
          "count": 2,
          "manufacturer": "GROW3",
          "model": "TopLight MH Model-300W-22G12"
        },
        "dehumidifier": {
          "selectedEquipment": [
            {
              "category": "dehumidifier",
              "vendor": "Quest",
              "model": "Quest Dual 155",
              "capacity": "155 pints/day",
              "control": "WiFi",
              "count": 1
            }
          ],
          "wifi": true,
          "wired": false,
          "count": 1,
          "manufacturer": "Quest",
          "model": "Quest Dual 155"
        }
      },
      "_categoryProgress": {
        "light": {
          "selectedEquipment": [
            {
              "category": "light",
              "vendor": "GROW3",
              "model": "TopLight MH Model-300W-22G12",
              "count": 2,
              "zone": "Propagation North"
            }
          ]
        },
        "dehumidifier": {
          "selectedEquipment": [
            {
              "category": "dehumidifier",
              "vendor": "Quest",
              "model": "Quest Dual 155",
              "capacity": "155 pints/day",
              "control": "WiFi",
              "count": 1
            }
          ]
        }
      }
    },
    {
      "id": "room-greenreach",
      "name": "GreenReach Demo Lab",
      "location": "Main Campus",
      "hardwareCats": ["light", "sensors"],
      "hardwareOrder": ["light", "sensors"],
      "layout": {
        "type": "benches",
        "rows": 1,
        "racks": 1,
        "levels": 1
      },
      "zones": ["Demo Row"],
      "fixtures": [
        {
          "id": "fixture-greenreach-demo",
          "vendor": "GROW3",
          "model": "TopLight MH Model-300W-22G12",
          "count": 1,
          "zone": "Demo Row"
        }
      ],
      "controlMethod": "controller",
      "devices": [
        { "id": "light-006", "type": "light" }
      ],
      "sensors": {
        "categories": ["environment"],
        "placements": {
          "environment": [
            { "type": "Temp/Humidity", "location": "center canopy" }
          ]
        }
      },
      "energy": "120V dedicated",
      "energyHours": 16,
      "targetPpfd": 400,
      "photoperiod": 16,
      "connectivity": {
        "hasHub": false,
        "wifi": true
      },
      "roles": {
        "admin": ["demo.operator"],
        "operator": ["demo.tech"],
        "viewer": []
      },
      "grouping": {
        "groups": ["greenreach-demo"],
        "planId": "demo-propagation",
        "scheduleId": "schedule-demo-16h"
      },
      "seriesCount": 1,
      "category": {
        "light": {
          "selectedEquipment": [
            {
              "category": "light",
              "vendor": "GROW3",
              "model": "TopLight MH Model-300W-22G12",
              "count": 1,
              "zone": "Demo Row"
            }
          ],
          "wifi": true,
          "wired": false,
          "count": 1,
          "manufacturer": "GROW3",
          "model": "TopLight MH Model-300W-22G12"
        },
        "sensors": {
          "selectedEquipment": [
            {
              "category": "sensors",
              "vendor": "GreenReach",
              "model": "EnviroSense",
              "count": 1
            }
          ],
          "wifi": true,
          "wired": false,
          "count": 1,
          "manufacturer": "GreenReach",
          "model": "EnviroSense"
        }
      },
      "_categoryProgress": {
        "light": {
          "selectedEquipment": [
            {
              "category": "light",
              "vendor": "GROW3",
              "model": "TopLight MH Model-300W-22G12",
              "count": 1,
              "zone": "Demo Row"
            }
          ]
        },
        "sensors": {
          "selectedEquipment": [
            {
              "category": "sensors",
              "vendor": "GreenReach",
              "model": "EnviroSense",
              "count": 1
            }
          ]
        }
      }
    },
    {
      "id": "room-flower",
      "name": "Flower Bay",
      "location": "Main Campus",
      "hardwareCats": ["light", "hvac"],
      "hardwareOrder": ["light", "hvac"],
      "layout": {
        "type": "racks",
        "rows": 3,
        "racks": 2,
        "levels": 2
      },
      "zones": ["Flower East"],
      "fixtures": [
        {
          "id": "fixture-flower-toplight",
          "vendor": "GROW3",
          "model": "TopLight MH Model-300W-22G12",
          "count": 3,
          "zone": "Flower East"
        }
      ],
      "controlMethod": "controller",
      "devices": [
        { "id": "light-003", "type": "light" },
        { "id": "light-004", "type": "light" },
        { "id": "light-005", "type": "light" }
      ],
      "sensors": {
        "categories": ["environment"],
        "placements": {
          "environment": [
            { "type": "Temp/Humidity", "location": "center canopy" },
            { "type": "PPFD", "location": "south rack" }
          ]
        }
      },
      "energy": "208V three-phase",
      "energyHours": 12,
      "targetPpfd": 850,
      "photoperiod": 12,
      "connectivity": {
        "hasHub": true,
        "hubType": "GrowLink",
        "hubIp": "192.168.1.60",
        "cloudTenant": "GrowLink"
      },
      "roles": {
        "admin": ["alex.nguyen"],
        "operator": ["maria.lopez"],
        "viewer": ["samantha.hughes"]
      },
      "grouping": {
        "groups": ["flower-east"],
        "planId": "flower-full-cycle",
        "scheduleId": "schedule-flower-12h"
      },
      "seriesCount": 2,
      "category": {
        "light": {
          "selectedEquipment": [
            {
              "category": "light",
              "vendor": "GROW3",
              "model": "TopLight MH Model-300W-22G12",
              "count": 3,
              "zone": "Flower East"
            }
          ],
          "wifi": true,
          "wired": false,
          "count": 3,
          "manufacturer": "GROW3",
          "model": "TopLight MH Model-300W-22G12"
        },
        "hvac": {
          "selectedEquipment": [
            {
              "category": "hvac",
              "vendor": "TrolMaster",
              "model": "Hydro-X Pro",
              "control": "Modbus",
              "count": 1
            }
          ],
          "wifi": false,
          "wired": true,
          "count": 1,
          "manufacturer": "TrolMaster",
          "model": "Hydro-X Pro"
        }
      },
      "_categoryProgress": {
        "light": {
          "selectedEquipment": [
            {
              "category": "light",
              "vendor": "GROW3",
              "model": "TopLight MH Model-300W-22G12",
              "count": 3,
              "zone": "Flower East"
            }
          ]
        }
      }
    }
  ]
}
